wowtello/__init__.py
wowtello/wowtello.py
wow_tello-1.4.0.dist-info/METADATA
wow_tello-1.4.0.dist-info/WHEEL
wow_tello-1.4.0.dist-info/top_level.txt
wow_tello-1.4.0.dist-info/RECORD
