Metadata-Version: 2.1
Name: wow-tello
Version: 1.4.0
Summary: Wow IoT Platform API libraries
Home-page: https://github.com/WOWSYSTEM/
Author: wowsystem, nobu
Author-email: contact@wowsystem.co.kr
License: UNKNOWN
Keywords: wowsystem,Drone,Tello,Tello Edu,Tello TT,DJI
Platform: UNKNOWN
Classifier: Programming Language :: Python :: 3.6
Classifier: Programming Language :: Python :: 3.7
Classifier: Programming Language :: Python :: 3.8
Classifier: Programming Language :: Python :: 3.9
Classifier: Programming Language :: Python :: 3.10
Requires-Python: >=3.6
